[
  {
    "ContainingType": "Petrol_Pump_Web_API.PresentationLayer.Controllers.AuthController",
    "Method": "Login",
    "RelativePath": "api/auth/login",
    "HttpMethod": "POST",
    "IsController": true,
    "Order": 0,
    "Parameters": [
      {
        "Name": "dto",
        "Type": "Petrol_Pump_Web_API.ApplicationLayer.DTOS.LoginDto",
        "IsRequired": true
      }
    ],
    "ReturnTypes": []
  },
  {
    "ContainingType": "Petrol_Pump_Web_API.PresentationLayer.Controllers.DispensingController",
    "Method": "Create",
    "RelativePath": "api/Dispensing",
    "HttpMethod": "POST",
    "IsController": true,
    "Order": 0,
    "Parameters": [
      {
        "Name": "DispenserNo",
        "Type": "System.String",
        "IsRequired": false
      },
      {
        "Name": "QuantityFilled",
        "Type": "System.Decimal",
        "IsRequired": false
      },
      {
        "Name": "VehicleNumber",
        "Type": "System.String",
        "IsRequired": false
      },
      {
        "Name": "PaymentMode",
        "Type": "System.String",
        "IsRequired": false
      },
      {
        "Name": "PaymentProofPath",
        "Type": "Microsoft.AspNetCore.Http.IFormFile",
        "IsRequired": false
      }
    ],
    "ReturnTypes": []
  },
  {
    "ContainingType": "Petrol_Pump_Web_API.PresentationLayer.Controllers.DispensingController",
    "Method": "GetAll",
    "RelativePath": "api/Dispensing",
    "HttpMethod": "GET",
    "IsController": true,
    "Order": 0,
    "Parameters": [
      {
        "Name": "dispenserNo",
        "Type": "System.String",
        "IsRequired": false
      },
      {
        "Name": "paymentMode",
        "Type": "System.String",
        "IsRequired": false
      },
      {
        "Name": "startDate",
        "Type": "System.Nullable\u00601[[System.DateTime, System.Private.CoreLib, Version=10.0.0.0, Culture=neutral, PublicKeyToken=7cec85d7bea7798e]]",
        "IsRequired": false
      },
      {
        "Name": "endDate",
        "Type": "System.Nullable\u00601[[System.DateTime, System.Private.CoreLib, Version=10.0.0.0, Culture=neutral, PublicKeyToken=7cec85d7bea7798e]]",
        "IsRequired": false
      }
    ],
    "ReturnTypes": []
  },
  {
    "ContainingType": "Petrol_Pump_Web_API.PresentationLayer.Controllers.WeatherForecastController",
    "Method": "Get",
    "RelativePath": "WeatherForecast",
    "HttpMethod": "GET",
    "IsController": true,
    "Order": 0,
    "Parameters": [],
    "ReturnTypes": [
      {
        "Type": "System.Collections.Generic.IEnumerable\u00601[[Petrol_Pump_Web_API.WeatherForecast, Petrol_Pump_Web_API, Version=1.0.0.0, Culture=neutral, PublicKeyToken=null]]",
        "MediaTypes": [
          "text/plain",
          "application/json",
          "text/json"
        ],
        "StatusCode": 200
      }
    ],
    "EndpointName": "GetWeatherForecast"
  }
]